{"skeleton":{"hash":"GxnazlbCfi8TdnFnKEh9tku7NkA","spine":"3.8.99"},"bones":[{"name":"root"}],"slots":[{"name":"sheetSlot","bone":"root","blend":"additive"}],"skins":[{"name":"default","attachments":{"sheetSlot":{"1":{"x":-6.97,"y":-13.02,"width":118,"height":76},"2":{"x":6.69,"y":1.24,"width":95,"height":42},"3":{"x":11.27,"y":3.22,"width":95,"height":115},"4":{"x":6.32,"y":33.07,"width":80,"height":93},"5":{"x":6.7,"y":26.13,"width":118,"height":105},"6":{"x":9.26,"y":35.06,"width":118,"height":141},"7":{"x":13.2,"y":48.15,"width":118,"height":160},"8":{"x":18.11,"y":73.38,"width":118,"height":215},"9":{"x":18.93,"y":81.03,"width":135,"height":181},"10":{"x":22.88,"y":91.9,"width":135,"height":239},"11":{"x":22.82,"y":126.15,"width":135,"height":274},"12":{"x":25.28,"y":133.73,"width":135,"height":295},"13":{"x":30.37,"y":152.17,"width":144,"height":350},"14":{"x":33.71,"y":207.18,"width":144,"height":424},"15":{"x":34.37,"y":198.95,"width":144,"height":426},"16":{"x":26.83,"y":187.63,"width":129,"height":376},"17":{"x":18.64,"y":146.8,"width":162,"height":300},"18":{"x":24.84,"y":188.43,"width":162,"height":397},"19":{"x":26.53,"y":189.55,"width":154,"height":403},"20":{"x":26.37,"y":187.57,"width":154,"height":376},"21":{"x":21.62,"y":149.73,"width":138,"height":334},"22":{"x":21.77,"y":128,"width":138,"height":281},"23":{"x":31.62,"y":175.23,"width":138,"height":367},"24":{"x":32.28,"y":174.57,"width":138,"height":346},"25":{"x":11.27,"y":101.79,"width":133,"height":285},"26":{"x":11.15,"y":69.84,"width":133,"height":201},"27":{"x":35.9,"y":126.82,"width":133,"height":270},"28":{"x":19.69,"y":93.16,"width":163,"height":186},"29":{"x":8.23,"y":18.45,"width":105,"height":116},"30":{"x":22.4,"y":67.19,"width":84,"height":148},"31":{"x":12.85,"y":52.04,"width":144,"height":97},"32":{"x":10.76,"y":13.29,"width":105,"height":86}}}}],"animations":{"Sprite":{"slots":{"sheetSlot":{"attachment":[{"name":"1"},{"time":0.0417,"name":"2"},{"time":0.0833,"name":"3"},{"time":0.125,"name":"4"},{"time":0.1667,"name":"5"},{"time":0.2083,"name":"6"},{"time":0.25,"name":"7"},{"time":0.2917,"name":"8"},{"time":0.3333,"name":"9"},{"time":0.375,"name":"10"},{"time":0.4167,"name":"11"},{"time":0.4583,"name":"12"},{"time":0.5,"name":"17"},{"time":0.5417,"name":"18"},{"time":0.5833,"name":"14"},{"time":0.625,"name":"15"},{"time":0.6667,"name":"16"},{"time":0.7083,"name":"19"},{"time":0.75,"name":"20"},{"time":0.7917,"name":"23"},{"time":0.8333,"name":"24"},{"time":0.875,"name":"21"},{"time":0.9167,"name":"22"},{"time":0.9583,"name":"27"},{"time":1,"name":"28"},{"time":1.0417,"name":"25"},{"time":1.0833,"name":"26"},{"time":1.125,"name":"30"},{"time":1.1667,"name":"31"},{"time":1.2083,"name":"29"},{"time":1.25,"name":"32"},{"time":1.2917,"name":null}]}}}}}